{
	"Price" : {
	    "Quantity" : "0.90",
	    "Currency" : "Euro"
	},
		"Name" : "Guardsman",
		"pointValue" : "25",
		"ExpectedTime" : "35mn",
		"Story" : "Common soldier from a Hive, Cadia is here.",
		"Faction" : "Imperium of Men"
}
{
	"Price" : {
	    "Quantity" : "1.10",
	    "Currency" : "Euro"
	},
		"Name" : "Guardsman avec fuseur",
		"pointValue" : "30",
		"ExpectedTime" : "35mn",
		"Story" : "Common heavy soldier from a Hive, Cadia is here.",
		"Faction" : "Imperium of Men"
}
{
	"Price" : {
	    "Quantity" : "1",
	    "Currency" : "Euro"
	},
		"Name" : "Commissaire",
		"pointValue" : "28",
		"ExpectedTime" : "40mn",
		"Story" : "Common soldier from a Hive, Cadia is here.",
		"Faction" : "Imperium of Men"
}
{
    "Price" : {
        "Quantity" : "1.10",
        "Currency" : "Euro"
    },
    	"Name" : "Soldat de feu",
    	"pointValue" : "25",
    	"ExpectedTime" : "45mn",
    	"Story" : "Soldier from the great Tau empire.",
    	"Faction" : "Tau"
}
{
    "Price" : {
        "Quantity" : "1.10",
        "Currency" : "Euro"
    },
    	"Name" : "Armure Crysis",
    	"pointValue" : "78",
    	"ExpectedTime" : "70mn",
    	"Story" : "Shock Exo-Armor from the great Tau empire.",
    	"Faction" : "Tau"
}
